dap/__init__.py
dap/asyncserver.py
dap/base.py
dap/buffer.py
dap/client.py
dap/connection.py
dap/events.py
dap/handler.py
dap/requests.py
dap/responses.py
dap/server.py
dap/types.py
dap_python-0.5.0.dist-info/LICENSE
dap_python-0.5.0.dist-info/METADATA
dap_python-0.5.0.dist-info/WHEEL
dap_python-0.5.0.dist-info/RECORD
